ooda_flow_diagram/__init__.py
ooda_flow_diagram/base/__init__.py
ooda_flow_diagram/ooda/__init__.py
ooda_flow_diagram/ooda/basic.py
ooda_flow_diagram/ooda/img/25.png
ooda_flow_diagram/ooda/img/50.png
ooda_flow_diagram/ooda/img/75.png
ooda_flow_diagram/ooda/img/done.png
ooda_flow_diagram/ooda/img/start.png
ooda_flow_diagram-0.1.0.dist-info/LICENSE
ooda_flow_diagram-0.1.0.dist-info/WHEEL
ooda_flow_diagram-0.1.0.dist-info/METADATA
ooda_flow_diagram-0.1.0.dist-info/RECORD
