Metadata-Version: 2.1
Name: ooda-flow-diagram
Version: 0.1.0
Summary: This supports OODA Loop project.
Home-page: https://github.com/sabi2345/ooda_flow_diagram
License: MIT
Author: sabi2345
Requires-Python: >=3.8,<4.0
Classifier: License :: OSI Approved :: MIT License
Classifier: Programming Language :: Python :: 3
Classifier: Programming Language :: Python :: 3.8
Classifier: Programming Language :: Python :: 3.9
Requires-Dist: graphviz (>=0.16,<0.17)
Project-URL: Repository, https://github.com/sabi2345/ooda_flow_diagram
